<MedlineCitation Status="Completed">
<MedlineID>10011174</MedlineID>
<PMID>420717</PMID>
<DateCreated>
<Year>1979</Year>
<Month>04</Month>
<Day>28</Day>
</DateCreated>
<DateCompleted>
<Year>1979</Year>
<Month>04</Month>
<Day>28</Day>
</DateCompleted>
<DateRevised>
<Year>2000</Year>
<Month>12</Month>
<Day>18</Day>
</DateRevised>
<Article>
<Journal>
<ISSN>0004-3591</ISSN>
<JournalIssue>
<Volume>22</Volume>
<Issue>3</Issue>
<PubDate>
<Year>1979</Year>
<Month>Mar</Month>
</PubDate>
</JournalIssue>
</Journal>
<ArticleTitle>Atlantoaxial subluxation as a complication of early ankylosing spondylitis. Two cases reports and a review of the literature.</ArticleTitle>
<Pagination>
<MedlinePgn>273-6</MedlinePgn>
</Pagination>
<AuthorList>
<Author>
<LastName>Sorin</LastName>
<ForeName>S</ForeName>
<Initials>S</Initials>
</Author>
<Author>
<LastName>Askari</LastName>
<ForeName>A</ForeName>
<Initials>A</Initials>
</Author>
<Author>
<LastName>Moskowitz</LastName>
<ForeName>R W</ForeName>
<Initials>RW</Initials>
</Author>
</AuthorList>
<Language>eng</Language>
<PublicationTypeList>
<PublicationType>Journal Article</PublicationType>
</PublicationTypeList>
</Article>
<MedlineJournalInfo>
<Country>UNITED STATES</Country>
<MedlineTA>Arthritis Rheum</MedlineTA>
<NlmUniqueID>0370605</NlmUniqueID>
</MedlineJournalInfo>
<CitationSubset>AIM</CitationSubset>
<CitationSubset>IM</CitationSubset>
<MeshHeadingList>
<MeshHeading>
<DescriptorName>Adult</DescriptorName>
</MeshHeading>
<MeshHeading>
<DescriptorName>Atlas</DescriptorName>
<QualifierName MajorTopicYN="Y">injuries</QualifierName>
</MeshHeading>
<MeshHeading>
<DescriptorName>Case Report</DescriptorName>
</MeshHeading>
<MeshHeading>
<DescriptorName>Dislocations</DescriptorName>
<QualifierName MajorTopicYN="Y">etiology</QualifierName>
<QualifierName>radiography</QualifierName>
</MeshHeading>
<MeshHeading>
<DescriptorName>Human</DescriptorName>
</MeshHeading>
<MeshHeading>
<DescriptorName>Male</DescriptorName>
</MeshHeading>
<MeshHeading>
<DescriptorName>Spinal Cord Compression</DescriptorName>
<QualifierName>etiology</QualifierName>
</MeshHeading>
<MeshHeading>
<DescriptorName>Spinal Injuries</DescriptorName>
<QualifierName>etiology</QualifierName>
<QualifierName>radiography</QualifierName>
</MeshHeading>
<MeshHeading>
<DescriptorName>Spondylitis, Ankylosing</DescriptorName>
<QualifierName MajorTopicYN="Y">complications</QualifierName>
<QualifierName>radiography</QualifierName>
</MeshHeading>
<MeshHeading>
<DescriptorName>Synovitis</DescriptorName>
<QualifierName>complications</QualifierName>
<QualifierName>radiography</QualifierName>
</MeshHeading>
</MeshHeadingList>
</MedlineCitation>
