<MedlineCitation Status="Completed">
<MedlineID>10011977</MedlineID>
<PMID>421192</PMID>
<DateCreated>
<Year>1979</Year>
<Month>05</Month>
<Day>24</Day>
</DateCreated>
<DateCompleted>
<Year>1979</Year>
<Month>05</Month>
<Day>24</Day>
</DateCompleted>
<DateRevised>
<Year>2000</Year>
<Month>12</Month>
<Day>18</Day>
</DateRevised>
<Article>
<Journal>
<ISSN>0008-543X</ISSN>
<JournalIssue>
<Volume>43</Volume>
<Issue>2</Issue>
<PubDate>
<Year>1979</Year>
<Month>Feb</Month>
</PubDate>
</JournalIssue>
</Journal>
<ArticleTitle>Group counseling in adult patients with advanced cancer.</ArticleTitle>
<Pagination>
<MedlinePgn>760-6</MedlinePgn>
</Pagination>
<Abstract>
<AbstractText>The effect of a structured, interdisciplinary group counseling program was studied in 30 newly diagnosed adult patients with advanced cancer. These were compared to 30 patients who did not undergo group counseling. Group counseling resulted in a significant improvement in patient perception and self-concept. This structured educational and psychological support program provided a mutal support experience for newly diagnosed patients with advanced cancer.</AbstractText>
</Abstract>
<AuthorList>
<Author>
<LastName>Ferlic</LastName>
<ForeName>M</ForeName>
<Initials>M</Initials>
</Author>
<Author>
<LastName>Goldman</LastName>
<ForeName>A</ForeName>
<Initials>A</Initials>
</Author>
<Author>
<LastName>Kennedy</LastName>
<ForeName>B J</ForeName>
<Initials>BJ</Initials>
</Author>
</AuthorList>
<Language>eng</Language>
<PublicationTypeList>
<PublicationType>Journal Article</PublicationType>
</PublicationTypeList>
</Article>
<MedlineJournalInfo>
<Country>UNITED STATES</Country>
<MedlineTA>Cancer</MedlineTA>
<NlmUniqueID>0374236</NlmUniqueID>
</MedlineJournalInfo>
<CitationSubset>AIM</CitationSubset>
<CitationSubset>IM</CitationSubset>
<MeshHeadingList>
<MeshHeading>
<DescriptorName>Adult</DescriptorName>
</MeshHeading>
<MeshHeading>
<DescriptorName MajorTopicYN="Y">Counseling</DescriptorName>
</MeshHeading>
<MeshHeading>
<DescriptorName>Education</DescriptorName>
</MeshHeading>
<MeshHeading>
<DescriptorName>Female</DescriptorName>
</MeshHeading>
<MeshHeading>
<DescriptorName>Human</DescriptorName>
</MeshHeading>
<MeshHeading>
<DescriptorName>Male</DescriptorName>
</MeshHeading>
<MeshHeading>
<DescriptorName>Middle Age</DescriptorName>
</MeshHeading>
<MeshHeading>
<DescriptorName>Neoplasms</DescriptorName>
<QualifierName>psychology</QualifierName>
<QualifierName MajorTopicYN="Y">therapy</QualifierName>
</MeshHeading>
<MeshHeading>
<DescriptorName>Psychological Tests</DescriptorName>
</MeshHeading>
<MeshHeading>
<DescriptorName>Psychotherapy, Group</DescriptorName>
</MeshHeading>
<MeshHeading>
<DescriptorName>Self Concept</DescriptorName>
</MeshHeading>
<MeshHeading>
<DescriptorName>Support, U.S. Gov't, P.H.S.</DescriptorName>
</MeshHeading>
</MeshHeadingList>
</MedlineCitation>
