<MedlineCitation Status="Completed">
<MedlineID>10011628</MedlineID>
<PMID>420971</PMID>
<DateCreated>
<Year>1979</Year>
<Month>05</Month>
<Day>24</Day>
</DateCreated>
<DateCompleted>
<Year>1979</Year>
<Month>05</Month>
<Day>24</Day>
</DateCompleted>
<DateRevised>
<Year>2000</Year>
<Month>12</Month>
<Day>18</Day>
</DateRevised>
<Article>
<Journal>
<ISSN>0007-1323</ISSN>
<JournalIssue>
<Volume>66</Volume>
<Issue>1</Issue>
<PubDate>
<Year>1979</Year>
<Month>Jan</Month>
</PubDate>
</JournalIssue>
</Journal>
<ArticleTitle>Long term follow-up of patients with gastric ulcers treated by vagotomy, pyloroplasty and ulcerectomy.</ArticleTitle>
<Pagination>
<MedlinePgn>46-7</MedlinePgn>
</Pagination>
<Abstract>
<AbstractText>Vagotomy and pyloroplasty with excision of the ulcer has been performed in a series of 90 patients with benign gastric ulcers. Long term follow-up has shown only 2 patients with recurrent, ulceration . Fifty-eight patients with more than 2 years' follow-up attended for personal interview, of whom 96 per cent had a satisfactory result.</AbstractText>
</Abstract>
<AuthorList>
<Author>
<LastName>Cade</LastName>
<ForeName>D</ForeName>
<Initials>D</Initials>
</Author>
<Author>
<LastName>Allan</LastName>
<ForeName>D</ForeName>
<Initials>D</Initials>
</Author>
</AuthorList>
<Language>eng</Language>
<PublicationTypeList>
<PublicationType>Journal Article</PublicationType>
</PublicationTypeList>
</Article>
<MedlineJournalInfo>
<Country>ENGLAND</Country>
<MedlineTA>Br J Surg</MedlineTA>
<NlmUniqueID>0372553</NlmUniqueID>
</MedlineJournalInfo>
<CitationSubset>AIM</CitationSubset>
<CitationSubset>IM</CitationSubset>
<MeshHeadingList>
<MeshHeading>
<DescriptorName>Duodenal Ulcer</DescriptorName>
<QualifierName>surgery</QualifierName>
</MeshHeading>
<MeshHeading>
<DescriptorName>Female</DescriptorName>
</MeshHeading>
<MeshHeading>
<DescriptorName>Follow-Up Studies</DescriptorName>
</MeshHeading>
<MeshHeading>
<DescriptorName>Human</DescriptorName>
</MeshHeading>
<MeshHeading>
<DescriptorName>Male</DescriptorName>
</MeshHeading>
<MeshHeading>
<DescriptorName>Methods</DescriptorName>
</MeshHeading>
<MeshHeading>
<DescriptorName>Middle Age</DescriptorName>
</MeshHeading>
<MeshHeading>
<DescriptorName>Pylorus</DescriptorName>
<QualifierName MajorTopicYN="Y">surgery</QualifierName>
</MeshHeading>
<MeshHeading>
<DescriptorName>Recurrence</DescriptorName>
</MeshHeading>
<MeshHeading>
<DescriptorName>Stomach Ulcer</DescriptorName>
<QualifierName MajorTopicYN="Y">surgery</QualifierName>
</MeshHeading>
<MeshHeading>
<DescriptorName MajorTopicYN="Y">Vagotomy</DescriptorName>
</MeshHeading>
</MeshHeadingList>
</MedlineCitation>
