<MedlineCitation Status="Completed">
<MedlineID>10011138</MedlineID>
<PMID>420701</PMID>
<DateCreated>
<Year>1979</Year>
<Month>04</Month>
<Day>28</Day>
</DateCreated>
<DateCompleted>
<Year>1979</Year>
<Month>04</Month>
<Day>28</Day>
</DateCompleted>
<DateRevised>
<Year>2000</Year>
<Month>12</Month>
<Day>18</Day>
</DateRevised>
<Article>
<Journal>
<ISSN>0067-8147</ISSN>
<JournalIssue>
<Issue>159</Issue>
<PubDate>
<Year>1979</Year>
</PubDate>
</JournalIssue>
</Journal>
<ArticleTitle>Teaching and training of the psychosomatic approach.</ArticleTitle>
<Pagination>
<MedlinePgn>15-22</MedlinePgn>
</Pagination>
<Abstract>
<AbstractText>In the United States, teaching and training of the psychosomatic approach relies upon (1) the application of psychosomatic concepts, such as reaction to stress, life change and illness, and neuroendocrine influences on disease process to the delivery of mental health services to the sick and dying through liaison programs, and (2) the focussing upon relevant methodology of psychological care in the context of American medicine with its growing knowledge of social implications of health care. Such methodology includes the teaching of data collection, substantive psychiatric disorders in the medically ill, supportive therapy and crisis intervention, psychopharmacology, emotional reaction to illness, and management of obstacles to a psychosocial approach. The resistance of nonpsychiatrist personnel to psychological factors and of psychiatric personnel to medical factors are obstacles which require particular emphasis in graduate and postgraduate training in this clinical area.</AbstractText>
</Abstract>
<AuthorList>
<Author>
<LastName>Greenhill</LastName>
<ForeName>M H</ForeName>
<Initials>MH</Initials>
</Author>
</AuthorList>
<Language>eng</Language>
<PublicationTypeList>
<PublicationType>Journal Article</PublicationType>
</PublicationTypeList>
</Article>
<MedlineJournalInfo>
<Country>SWITZERLAND</Country>
<MedlineTA>Bibl Psychiatr</MedlineTA>
<NlmUniqueID>0255452</NlmUniqueID>
</MedlineJournalInfo>
<CitationSubset>IM</CitationSubset>
<MeshHeadingList>
<MeshHeading>
<DescriptorName MajorTopicYN="Y">Education, Medical, Continuing</DescriptorName>
</MeshHeading>
<MeshHeading>
<DescriptorName MajorTopicYN="Y">Education, Medical, Graduate</DescriptorName>
</MeshHeading>
<MeshHeading>
<DescriptorName>Human</DescriptorName>
</MeshHeading>
<MeshHeading>
<DescriptorName>Psychosomatic Medicine</DescriptorName>
<QualifierName MajorTopicYN="Y">education</QualifierName>
</MeshHeading>
<MeshHeading>
<DescriptorName>United States</DescriptorName>
</MeshHeading>
</MeshHeadingList>
</MedlineCitation>
