<MedlineCitation Status="Completed">
<MedlineID>10011642</MedlineID>
<PMID>420981</PMID>
<DateCreated>
<Year>1979</Year>
<Month>05</Month>
<Day>23</Day>
</DateCreated>
<DateCompleted>
<Year>1979</Year>
<Month>05</Month>
<Day>23</Day>
</DateCompleted>
<DateRevised>
<Year>2000</Year>
<Month>12</Month>
<Day>18</Day>
</DateRevised>
<Article>
<Journal>
<ISSN>0007-1323</ISSN>
<JournalIssue>
<Volume>66</Volume>
<Issue>2</Issue>
<PubDate>
<Year>1979</Year>
<Month>Feb</Month>
</PubDate>
</JournalIssue>
</Journal>
<ArticleTitle>Gastric carcinoma and previous peptic ulceration.</ArticleTitle>
<Pagination>
<MedlinePgn>117-9</MedlinePgn>
</Pagination>
<Abstract>
<AbstractText>The incidence of patients with gastric carcinoma having had a previously diagnosed or suspected peptic ulcer was noted in two studies. These studies were the West Midlands Gastric Chemotherapy Trial (1974--6) and a retrospective study of patients presenting to the United Birmingham Hospitals with gastric carcinoma during the years 1958--62 and 1968--72. The incidence of patients found to have had a previous operation for duodenal ulcer or to have post-mortem evidence of one was 6.5 per cent and 5.7 per cent respectively. A radiologically proved duodenal ulcer had been identified in 5.5 per cent and 2.1 per cent respectively and the incidence of previous symptoms suggestive of a duodenal ulcer was 4.0 per cent and 5.2 per cent. These figures indicate the total incidence could be 12.97--16.0 per cent, which is much higher than previously reported. The mean time interval between operation for duodenal ulcer and the development of gastric carcinoma was much longer in patients having had a partial gastrectomy than in patients having had a vagotomy and drainage procedure. The incidence of previous benign gastric ulcers was 2.5 per cent and 0.9 per cent. Fifty-three per cent of patients having had a previous operation for duodenal ulceration were found to have an unresectable carcinoma, compared with the overall unresectable rate of 35 per cent.</AbstractText>
</Abstract>
<AuthorList>
<Author>
<LastName>Ellis</LastName>
<ForeName>D J</ForeName>
<Initials>DJ</Initials>
</Author>
<Author>
<LastName>Kingston</LastName>
<ForeName>R D</ForeName>
<Initials>RD</Initials>
</Author>
<Author>
<LastName>Brookes</LastName>
<ForeName>V S</ForeName>
<Initials>VS</Initials>
</Author>
<Author>
<LastName>Waterhouse</LastName>
<ForeName>J A</ForeName>
<Initials>JA</Initials>
</Author>
</AuthorList>
<Language>eng</Language>
<PublicationTypeList>
<PublicationType>Journal Article</PublicationType>
</PublicationTypeList>
</Article>
<MedlineJournalInfo>
<Country>ENGLAND</Country>
<MedlineTA>Br J Surg</MedlineTA>
<NlmUniqueID>0372553</NlmUniqueID>
</MedlineJournalInfo>
<CitationSubset>AIM</CitationSubset>
<CitationSubset>IM</CitationSubset>
<MeshHeadingList>
<MeshHeading>
<DescriptorName>Chronic Disease</DescriptorName>
</MeshHeading>
<MeshHeading>
<DescriptorName>Duodenal Ulcer</DescriptorName>
<QualifierName>complications</QualifierName>
<QualifierName>surgery</QualifierName>
</MeshHeading>
<MeshHeading>
<DescriptorName>Human</DescriptorName>
</MeshHeading>
<MeshHeading>
<DescriptorName>Peptic Ulcer</DescriptorName>
<QualifierName MajorTopicYN="Y">complications</QualifierName>
<QualifierName>surgery</QualifierName>
</MeshHeading>
<MeshHeading>
<DescriptorName>Postoperative Complications</DescriptorName>
</MeshHeading>
<MeshHeading>
<DescriptorName>Retrospective Studies</DescriptorName>
</MeshHeading>
<MeshHeading>
<DescriptorName>Stomach Neoplasms</DescriptorName>
<QualifierName MajorTopicYN="Y">etiology</QualifierName>
</MeshHeading>
<MeshHeading>
<DescriptorName>Time Factors</DescriptorName>
</MeshHeading>
</MeshHeadingList>
</MedlineCitation>
